SWELib/__init__.py
SWELib/main.py
SWELib-2.2.dist-info/METADATA
SWELib-2.2.dist-info/WHEEL
SWELib-2.2.dist-info/top_level.txt
SWELib-2.2.dist-info/RECORD
