Metadata-Version: 2.1
Name: SWELib
Version: 2.2
Requires-Dist: numpy (==1.23.5)
Requires-Dist: matplotlib (==3.7.1)
